README.rst
setup.py
src/zc/__init__.py
src/zc.htmlchecker.egg-info/PKG-INFO
src/zc.htmlchecker.egg-info/SOURCES.txt
src/zc.htmlchecker.egg-info/dependency_links.txt
src/zc.htmlchecker.egg-info/entry_points.txt
src/zc.htmlchecker.egg-info/namespace_packages.txt
src/zc.htmlchecker.egg-info/not-zip-safe
src/zc.htmlchecker.egg-info/requires.txt
src/zc.htmlchecker.egg-info/top_level.txt
src/zc/htmlchecker/README.rst
src/zc/htmlchecker/__init__.py
src/zc/htmlchecker/tests.py